amilib/__init__.py
amilib/ami_args.py
amilib/ami_bib.py
amilib/ami_corpus.py
amilib/ami_csv.py
amilib/ami_dict.py
amilib/ami_graph.py
amilib/ami_html.py
amilib/ami_integrate.py
amilib/ami_nlp.py
amilib/ami_pdf_libs.py
amilib/ami_svg.py
amilib/ami_util.py
amilib/amidriver.py
amilib/amix.py
amilib/bbox.py
amilib/constants.py
amilib/dict_args.py
amilib/file_lib.py
amilib/headless_lib.py
amilib/html_args.py
amilib/html_extra.py
amilib/html_generator.py
amilib/html_marker.py
amilib/pdf_args.py
amilib/search_args.py
amilib/util.py
amilib/wikimedia.py
amilib/xml_lib.py
amilib-0.5.3.dist-info/licenses/LICENSE
test/__init__.py
test/resources.py
test/test_all.py
test/test_amix.py
test/test_bib.py
test/test_classify.py
test/test_dict.py
test/test_extract_text.py
test/test_file.py
test/test_graph.py
test/test_headless.py
test/test_html.py
test/test_misc.py
test/test_nlp.py
test/test_pdf.py
test/test_pytest.py
test/test_search.py
test/test_stat.py
test/test_svg.py
test/test_unfccc_pdf.py
test/test_util.py
test/test_wikimedia.py
test/test_xml.py
amilib-0.5.3.dist-info/METADATA
amilib-0.5.3.dist-info/WHEEL
amilib-0.5.3.dist-info/entry_points.txt
amilib-0.5.3.dist-info/top_level.txt
amilib-0.5.3.dist-info/RECORD
