Metadata-Version: 2.4
Name: amilib
Version: 0.5.3
Summary: Document and dictionary download, cleaning, management
Home-page: https://github.com/petermr/amilib
Author: Peter Murray-Rust
Author-email: petermurrayrust@googlemail.com
License: Apache2
Keywords: text and data mining
Classifier: Development Status :: 3 - Alpha
Classifier: Intended Audience :: Developers
Classifier: License :: OSI Approved :: Apache Software License
Classifier: Programming Language :: Python :: 3.9
Classifier: Programming Language :: Python :: 3.10
Classifier: Programming Language :: Python :: 3.11
Classifier: Programming Language :: Python :: 3.12
Classifier: Natural Language :: English
Requires-Python: <3.13,>=3.9
License-File: LICENSE
Requires-Dist: lxml
Requires-Dist: nltk
Requires-Dist: pdfminer3
Requires-Dist: Pillow
Requires-Dist: setuptools
Requires-Dist: pdfplumber
Requires-Dist: requests
Requires-Dist: numpy
Requires-Dist: pandas
Requires-Dist: selenium
Requires-Dist: tinycss
Requires-Dist: SPARQLWrapper
Requires-Dist: Tkinterweb
Requires-Dist: webdriver-manager
Requires-Dist: scikit-learn
Dynamic: license-file
